<?xml version="1.0" encoding="utf-8"?>
<!-- Generated by User Thesaurus Plus : 2012-04-11 01:26:18 -->
<dtSearchUserThesaurus>
  <Item>
    <Name>andare</Name>
    <Synonyms>andare vado vai va andiamo andate vanno vada andiate vadano</Synonyms>
  </Item>
  <Item>
    <Name>avere</Name>
    <Synonyms>avere ho ebbi avevo avrò hai avesti avevi avrai ha ebbe aveva avrà abbiamo avemmo avevamo avremo avete aveste avevate avrete hanno ebbero avevano avranno</Synonyms>
  </Item>
  <Item>
    <Name>bere</Name>
    <Synonyms>bere beva beviamo beviate bevano</Synonyms>
  </Item>
  <Item>
    <Name>cercare</Name>
    <Synonyms>cercare</Synonyms>
  </Item>
  <Item>
    <Name>dare</Name>
    <Synonyms>dare do dai dà diamo date danno dia diate diano</Synonyms>
  </Item>
  <Item>
    <Name>dire</Name>
    <Synonyms>dire dico dici dice diciamo dite dicono dica diciate dicano</Synonyms>
  </Item>
  <Item>
    <Name>dovere</Name>
    <Synonyms>dovere devo devi deve dobbiamo dovete devono</Synonyms>
  </Item>
  <Item>
    <Name>essere</Name>
    <Synonyms>essere sono fui ero sarò sei fosti eri sarai è fu era sarà siamo fummo eravamo saremo siete foste eravate sarete furono erano saranno</Synonyms>
  </Item>
  <Item>
    <Name>fare</Name>
    <Synonyms>fare faccio fai fa facciamo fate fanno</Synonyms>
  </Item>
  <Item>
    <Name>piacere</Name>
    <Synonyms>piacere</Synonyms>
  </Item>
  <Item>
    <Name>potere</Name>
    <Synonyms>potere posso puoi può possiamo potete possono</Synonyms>
  </Item>
  <Item>
    <Name>sapere</Name>
    <Synonyms>sapere so sai sa sappiamo sapete sanno</Synonyms>
  </Item>
  <Item>
    <Name>stare</Name>
    <Synonyms>stare sto stai sta stiamo state stanno</Synonyms>
  </Item>
  <Item>
    <Name>tenere</Name>
    <Synonyms>tenere tengot tieni tiene teniamo tenete tengono</Synonyms>
  </Item>
  <Item>
    <Name>uscire</Name>
    <Synonyms>uscire esca uscíamo usciate escano</Synonyms>
  </Item>
  <Item>
    <Name>venire</Name>
    <Synonyms>venire vengo vieni viene veniamo venite vengono</Synonyms>
  </Item>
  <Item>
    <Name>vivere</Name>
    <Synonyms>vivere vivo vivi vive viviamo vivete vivono vivevo vivevi viveva vivevamo vivevate vivevano vissi vivesti visse vivemmo viveste vissero vivrò vivrai vivrà vivremo vivrete vivranno vissuto</Synonyms>
  </Item>
  <Item>
    <Name>volere</Name>
    <Synonyms>volere voglio vuoi vuole vogliamo volete vogliono</Synonyms>
  </Item>
</dtSearchUserThesaurus>